spectrust/__init__.py
spectrust/__version__.py
spectrust/_spectro.so
spectrust/api.py
spectrust/batch.py
spectrust-0.1.1.dist-info/LICENCE
spectrust-0.1.1.dist-info/METADATA
spectrust-0.1.1.dist-info/WHEEL
spectrust-0.1.1.dist-info/top_level.txt
spectrust-0.1.1.dist-info/RECORD
