Metadata-Version: 2.1
Name: spectrust
Version: 0.1.1
Summary: Blazing fast spectrogram generator.
Home-page: https://github.com/axegon/spectrust
Author: Alexander Ejbekov
Author-email: alexander@kialo.ai
License: MIT
Platform: UNKNOWN
Classifier: Development Status :: 4 - Beta
Classifier: Intended Audience :: Developers
Classifier: Natural Language :: English
Classifier: License :: OSI Approved :: MIT License
Classifier: Programming Language :: Python
Classifier: Programming Language :: Python :: 3.4
Classifier: Programming Language :: Python :: 3.5
Classifier: Programming Language :: Python :: 3.6
Classifier: Programming Language :: Python :: 3.7
Classifier: Programming Language :: Rust
